banavo_northbeam/NorthbeamService.py
banavo_northbeam/__init__.py
banavo_northbeam-0.0.42.dist-info/METADATA
banavo_northbeam-0.0.42.dist-info/WHEEL
banavo_northbeam-0.0.42.dist-info/top_level.txt
banavo_northbeam-0.0.42.dist-info/RECORD
