Metadata-Version: 2.1
Name: banavo-northbeam
Version: 0.0.42
Summary: Contains codes for the banavo-northbeam pipeline
Author: Naila Fatima
Author-email: naila.fatima@andromeda360.ai
